publify/__init__.py
publify/api.py
publify/file_doers.py
publify/publify.py
publify-0.2.5.dist-info/LICENSE
publify-0.2.5.dist-info/METADATA
publify-0.2.5.dist-info/WHEEL
publify-0.2.5.dist-info/entry_points.txt
publify-0.2.5.dist-info/top_level.txt
publify-0.2.5.dist-info/RECORD
