Metadata-Version: 2.1
Name: publify
Version: 0.2.5
Summary: A CLI for publishing sites to Netlify and assigning custom domains to them.
Home-page: https://github.com/zevaverbach/publify
Author: Zev Averbach
Author-email: zev@averba.ch
License: MIT
Classifier: Development Status :: 3 - Alpha
Classifier: Intended Audience :: Developers
Classifier: License :: OSI Approved :: MIT License
Classifier: Programming Language :: Python :: 3
Classifier: Programming Language :: Python :: 3.10
Classifier: Programming Language :: Python :: 3.11
Requires-Python: >=3.10
License-File: LICENSE
Requires-Dist: requests
